loe_simp_app_fw/__init__.py
loe_simp_app_fw/__main__.py
loe_simp_app_fw/cacher.py
loe_simp_app_fw/config.py
loe_simp_app_fw/csvnia.py
loe_simp_app_fw/exit.py
loe_simp_app_fw/helper.py
loe_simp_app_fw/notebook.py
loe_simp_app_fw/prometheus.py
loe_simp_app_fw/request_handler.py
loe_simp_app_fw/cacher/__init__.py
loe_simp_app_fw/cacher/exception.py
loe_simp_app_fw/cacher/manager.py
loe_simp_app_fw/cacher/model.py
loe_simp_app_fw/logger/__init__.py
loe_simp_app_fw/logger/backend_m.py
loe_simp_app_fw/logger/backend_s.py
loe_simp_app_fw/logger/frontend.py
loe_simp_app_fw/logger/middleware.py
loe_simp_app_fw/logger/model.py
loe_simp_app_fw/start/__init__.py
loe_simp_app_fw/start/default.py
loe_simp_app_fw/start/main.py
tests/__init__.py
tests/integration/__init__.py
tests/integration/cacher_demo.py
tests/integration/logging_demo.py
tests/integration/prometheus_demo.py
tests/unit/__init__.py
tests/unit/logging.py
loe_simp_app_fw-2.10.11.dist-info/LICENSE
loe_simp_app_fw-2.10.11.dist-info/METADATA
loe_simp_app_fw-2.10.11.dist-info/WHEEL
loe_simp_app_fw-2.10.11.dist-info/top_level.txt
loe_simp_app_fw-2.10.11.dist-info/RECORD
