Metadata-Version: 2.1
Name: loe_simp_app_fw
Version: 2.10.11
Summary: A super simple python app framework that includes a logger and a config manager. Also usable in jupyter notebook.
Author-email: loeeeee <95266635+loeeeee@users.noreply.github.com>
Project-URL: Homepage, https://github.com/loeeeee/loe-simp-app-fw
Project-URL: Issues, https://github.com/loeeeee/loe-simp-app-fw/issues
Keywords: framework,logger,config mangager
Classifier: Programming Language :: Python :: 3
Classifier: License :: OSI Approved :: GNU General Public License v3 (GPLv3)
Classifier: Operating System :: OS Independent
Requires-Python: >=3.8
License-File: LICENSE
Requires-Dist: pyyaml
Requires-Dist: requests
